mxlite_sdk-0.3.9.data/purelib/mxlite/__init__.py
mxlite_sdk-0.3.9.data/purelib/mxlite/deployer.py
mxlite_sdk-0.3.9.data/purelib/mxlite/mxlite.py
mxlite_sdk-0.3.9.data/purelib/mxlite/types.py
mxlite_sdk-0.3.9.data/purelib/mxlite/utils.py
mxlite_sdk-0.3.9.data/purelib/mxlite/bin/.placeholder
mxlite_sdk-0.3.9.data/purelib/mxlite/bin/mxa-linux-arm64
mxlite_sdk-0.3.9.data/purelib/mxlite/bin/mxa-linux-x86_64
mxlite_sdk-0.3.9.data/purelib/mxlite/bin/mxd-windows-x86_64.exe
mxlite_sdk-0.3.9.dist-info/METADATA
mxlite_sdk-0.3.9.dist-info/WHEEL
mxlite_sdk-0.3.9.dist-info/top_level.txt
mxlite_sdk-0.3.9.dist-info/RECORD
