Metadata-Version: 2.4
Name: mxlite-sdk
Version: 0.3.9
Summary: Python SDK for mxlite
Home-page: https://github.com/EM-GeekLab/mxlite-python-sdk
Author: PEScn
Author-email: PEScn <pescn@115lab.club>
Project-URL: Homepage, https://github.com/EM-GeekLab/mxlite-python-sdk
Project-URL: Repository, https://github.com/EM-GeekLab/mxlite-python-sdk
Project-URL: Documentation, https://github.com/EM-GeekLab/mxlite-python-sdk/wiki
Classifier: Development Status :: 2 - Pre-Alpha
Classifier: Intended Audience :: Developers
Classifier: Programming Language :: Python :: 3
Classifier: Programming Language :: Python :: 3.10
Classifier: Programming Language :: Python :: 3.11
Classifier: Programming Language :: Python :: 3.12
Classifier: Programming Language :: Python :: 3.13
Classifier: Programming Language :: Python :: 3.14
Classifier: Topic :: Software Development :: Libraries
Classifier: Topic :: System :: Installation/Setup
Classifier: Topic :: System :: Networking
Classifier: Topic :: System :: Operating System
Classifier: Topic :: System :: Shells
Classifier: Topic :: System :: Systems Administration
Requires-Python: >=3.10
Requires-Dist: aiohttp>=3.11.18
Requires-Dist: pydantic>=2.10.0
Provides-Extra: deploy
Requires-Dist: asyncssh>=2.14.0; extra == "deploy"
Dynamic: author
Dynamic: home-page
Dynamic: requires-python
